auth0_server_python/auth_schemes/__init__.py
auth0_server_python/auth_schemes/bearer_auth.py
auth0_server_python/auth_server/__init__.py
auth0_server_python/auth_server/my_account_client.py
auth0_server_python/auth_server/server_client.py
auth0_server_python/auth_types/__init__.py
auth0_server_python/encryption/__init__.py
auth0_server_python/encryption/encrypt.py
auth0_server_python/error/__init__.py
auth0_server_python/store/__init__.py
auth0_server_python/store/abstract.py
auth0_server_python/tests/test_my_account_client.py
auth0_server_python/tests/test_server_client.py
auth0_server_python/utils/__init__.py
auth0_server_python/utils/helpers.py
auth0_server_python-1.0.0b7.dist-info/METADATA
auth0_server_python-1.0.0b7.dist-info/WHEEL
auth0_server_python-1.0.0b7.dist-info/licenses/LICENSE
auth0_server_python-1.0.0b7.dist-info/RECORD
