Metadata-Version: 2.4
Name: auth0-server-python
Version: 1.0.0b7
Summary: Auth0 server-side Python SDK
License: MIT
License-File: LICENSE
Author: Auth0
Author-email: support@okta.com
Requires-Python: >=3.9
Classifier: License :: OSI Approved :: MIT License
Classifier: Programming Language :: Python :: 3
Classifier: Programming Language :: Python :: 3.9
Classifier: Programming Language :: Python :: 3.10
Classifier: Programming Language :: Python :: 3.11
Classifier: Programming Language :: Python :: 3.12
Classifier: Programming Language :: Python :: 3.13
Classifier: Programming Language :: Python :: 3.14
Requires-Dist: authlib (>=1.2,<2.0)
Requires-Dist: cryptography (>=43.0.1)
Requires-Dist: httpx (>=0.28.1,<0.29.0)
Requires-Dist: jwcrypto (>=1.5.6,<2.0.0)
Requires-Dist: pydantic (>=2.10.6,<3.0.0)
Requires-Dist: pyjwt (>=2.8.0)
